aidirectory/__init__.py
aidirectory/cmdlet.py
aidirectory/parameters.yaml
aidirectory/Project DESCRIPTIVE PROJECT TITLE/compile.CMD
aidirectory/Project DESCRIPTIVE PROJECT TITLE/project parameters.yaml
aidirectory/runner.py
aidirectory/utils.py
aidirectory-0.2.10.dist-info/WHEEL
aidirectory-0.2.10.dist-info/METADATA
aidirectory-0.2.10.dist-info/RECORD
