Metadata-Version: 2.1
Name: aidirectory
Version: 0.2.10
Summary: 
Author: mjaquier
Author-email: mjaquier@me.com
Requires-Python: >=3.8,<3.9
Classifier: Programming Language :: Python :: 3
Classifier: Programming Language :: Python :: 3.8
Requires-Dist: PyYAML (>=5.3.1,<6.0.0)
Requires-Dist: aihelper (>=0.1.22,<0.2.0)
Requires-Dist: oyaml (>=0.9,<0.10)
Requires-Dist: simplelogging (>=0.10.0,<0.11.0)
